{
  "gufang_id": "guzhenren:hua_shi_gu_gu_fang",
  "base_success": 0.5,
  "inputs": [
    {
      "item": "guzhenren:gucaiyuanshi",
      "count": 1
    },
    {
      "item": "guzhenren:zhi_xin_cao_gen",
      "count": 1
    },
    {
      "item": "minecraft:porkchop",
      "count": 1
    },
    {
      "item": "minecraft:black_dye",
      "count": 1
    },
    {
      "item": "minecraft:white_dye",
      "count": 1
    }
  ],
  "output": {
    "item": "guzhenren:hua_shi_gu",
    "count": 1
  }
}
